url_finder/__init__.py
url_finder-0.1.1.dist-info/LICENSE
url_finder-0.1.1.dist-info/METADATA
url_finder-0.1.1.dist-info/WHEEL
url_finder-0.1.1.dist-info/top_level.txt
url_finder-0.1.1.dist-info/RECORD
