Metadata-Version: 2.1
Name: url-finder
Version: 0.1.1
Summary: An easy utility to extract links from text.
Home-page: https://github.com/kajdev/url-finder
Author: kajdev
License: UNKNOWN
Platform: UNKNOWN
Classifier: Programming Language :: Python :: 3
Classifier: License :: OSI Approved :: MIT License
Classifier: Operating System :: OS Independent
License-File: LICENSE
